[
    {
        "generation": 1,
        "fitness": -437779.07613044535,
        "params": {
            "tau_wand": 0.08112832509034473,
            "tau_speicher": 0.1684178851542646,
            "tau_raum": 7.640986351385209,
            "fensterfaktor": 9.98894568954159e-05
        }
    },
    {
        "generation": 2,
        "fitness": -437779.07613044535,
        "params": {
            "tau_wand": 0.08112832509034473,
            "tau_speicher": 0.1684178851542646,
            "tau_raum": 7.640986351385209,
            "fensterfaktor": 9.98894568954159e-05
        }
    },
    {
        "generation": 3,
        "fitness": -437779.07613044535,
        "params": {
            "tau_wand": 0.08112832509034473,
            "tau_speicher": 0.1684178851542646,
            "tau_raum": 7.640986351385209,
            "fensterfaktor": 9.98894568954159e-05
        }
    },
    {
        "generation": 4,
        "fitness": -437779.07613044535,
        "params": {
            "tau_wand": 0.08112832509034473,
            "tau_speicher": 0.1684178851542646,
            "tau_raum": 7.640986351385209,
            "fensterfaktor": 9.98894568954159e-05
        }
    },
    {
        "generation": 5,
        "fitness": -435132.2772017285,
        "params": {
            "tau_wand": 0.061341607472746223,
            "tau_speicher": 0.10645030902427241,
            "tau_raum": 7.659851588576203,
            "fensterfaktor": 0.00011027506105855102
        }
    },
    {
        "generation": 6,
        "fitness": -435132.2772017285,
        "params": {
            "tau_wand": 0.061341607472746223,
            "tau_speicher": 0.10645030902427241,
            "tau_raum": 7.659851588576203,
            "fensterfaktor": 0.00011027506105855102
        }
    },
    {
        "generation": 7,
        "fitness": -434527.753907508,
        "params": {
            "tau_wand": 0.05308336879696283,
            "tau_speicher": 0.08029505048181654,
            "tau_raum": 7.590471841544038,
            "fensterfaktor": 0.00011411496450954745
        }
    },
    {
        "generation": 8,
        "fitness": -434527.753907508,
        "params": {
            "tau_wand": 0.05308336879696283,
            "tau_speicher": 0.08029505048181654,
            "tau_raum": 7.590471841544038,
            "fensterfaktor": 0.00011411496450954745
        }
    },
    {
        "generation": 9,
        "fitness": -433348.78605595196,
        "params": {
            "tau_wand": 0.05392496612887104,
            "tau_speicher": 0.07956040855670637,
            "tau_raum": 8.226587112191108,
            "fensterfaktor": 0.00010742395606474153
        }
    },
    {
        "generation": 10,
        "fitness": -433348.78605595196,
        "params": {
            "tau_wand": 0.05392496612887104,
            "tau_speicher": 0.07956040855670637,
            "tau_raum": 8.226587112191108,
            "fensterfaktor": 0.00010742395606474153
        }
    }
]